eoapi/auth_utils/__init__.py
eoapi/auth_utils/auth.py
eoapi/auth_utils/config.py
eoapi/auth_utils/errors.py
eoapi/auth_utils/types.py
eoapi_auth_utils-0.4.1.dist-info/METADATA
eoapi_auth_utils-0.4.1.dist-info/WHEEL
eoapi_auth_utils-0.4.1.dist-info/entry_points.txt
eoapi_auth_utils-0.4.1.dist-info/licenses/LICENSE
eoapi_auth_utils-0.4.1.dist-info/RECORD
