Metadata-Version: 2.1
Name: eoapi-auth-utils
Version: 0.4.1
Summary: Authentication & authorization helpers for eoAPI
Author-Email: Anthony Lukach <anthony@developmentseed.org>
License: MIT License
Requires-Python: >=3.8
Requires-Dist: cryptography>=43.0.0
Requires-Dist: fastapi>=0.7.0
Requires-Dist: pyjwt>=2.9.0
Provides-Extra: lint
Requires-Dist: pre-commit; extra == "lint"
Provides-Extra: testing
Requires-Dist: coverage; extra == "testing"
Requires-Dist: httpx>=0.27.0; extra == "testing"
Requires-Dist: jwcrypto>=1.5.6; extra == "testing"
Requires-Dist: pytest>=6.0; extra == "testing"
